episcope/__init__.py
episcope/app/__init__.py
episcope/app/__main__.py
episcope/app/core.py
episcope/app/state.py
episcope/library/__init__.py
episcope/library/io/__init__.py
episcope/library/io/v1_2/__init__.py
episcope/library/io/v1_2/ensemble.py
episcope/library/io/v1_2/experiment.py
episcope/library/io/v1_2/timestep.py
episcope/library/viz/alignment.py
episcope/library/viz/common.py
episcope/library/viz/data_source.py
episcope/library/viz/display.py
episcope/library/viz/visualization.py
episcope-0.3.3.dist-info/METADATA
episcope-0.3.3.dist-info/WHEEL
episcope-0.3.3.dist-info/entry_points.txt
episcope-0.3.3.dist-info/RECORD
