Metadata-Version: 2.4
Name: episcope
Version: 0.3.3
Summary: A visualization tool for 4D genomics datasets
Project-URL: Homepage, https://github.com/epicsuite/episcope
Project-URL: Bug Tracker, https://github.com/epicsuite/episcope/issues
Project-URL: Changelog, https://github.com/epicsuite/episcope/releases
Author-email: Alessandro Genova <alessandro.genova@kitware.com>
Classifier: Development Status :: 5 - Production/Stable
Classifier: Intended Audience :: Developers
Classifier: Intended Audience :: Science/Research
Classifier: License :: OSI Approved :: MIT License
Classifier: Operating System :: OS Independent
Classifier: Programming Language :: Python
Classifier: Programming Language :: Python :: 3
Classifier: Topic :: Scientific/Engineering
Requires-Python: >=3.10
Requires-Dist: pyproj
Requires-Dist: pyyaml
Requires-Dist: trame
Requires-Dist: trame-components
Requires-Dist: trame-plotly
Requires-Dist: trame-vtk
Requires-Dist: trame-vuetify
Provides-Extra: dev
Requires-Dist: nox; extra == 'dev'
Requires-Dist: pre-commit; extra == 'dev'
Requires-Dist: pytest-cov>=3; extra == 'dev'
Requires-Dist: pytest>=6; extra == 'dev'
Requires-Dist: ruff; extra == 'dev'
Provides-Extra: docs
Requires-Dist: furo>=2023.08.17; extra == 'docs'
Requires-Dist: myst-parser>=0.13; extra == 'docs'
Requires-Dist: sphinx-autodoc-typehints; extra == 'docs'
Requires-Dist: sphinx-copybutton; extra == 'docs'
Requires-Dist: sphinx>=7.0; extra == 'docs'
Provides-Extra: test
Requires-Dist: nox; extra == 'test'
Requires-Dist: pytest-cov>=3; extra == 'test'
Requires-Dist: pytest>=6; extra == 'test'
